{
    "appId": "cn.cnoctave.ottohub-electron",
    "productName": "ottohub-electron",
    "buildNumber": "2025.10.1",
    "icon": "logo.png",
    "directories": {
        "output": "dist"
    },
    "publish": [
        {
        "provider": "github",
        "owner": "CNOCTAVE",
        "repo": "ottohub-electron",
        "releaseType": "release"
        }
    ],
    "mac": {
        "artifactName": "${name}-${version}-${os}-${arch}.${ext}",
        "target": [
            {
                "target": "pkg",
                "arch": [
                    "universal"
                ]
            }
        ]
    }
}